simplygo/API.py
simplygo/Constants.py
simplygo/JsonFields.py
simplygo/Utility.py
simplygo/__init__.py
simplygopy-2021.5.1.dist-info/LICENSE
simplygopy-2021.5.1.dist-info/METADATA
simplygopy-2021.5.1.dist-info/WHEEL
simplygopy-2021.5.1.dist-info/top_level.txt
simplygopy-2021.5.1.dist-info/RECORD
