Metadata-Version: 2.1
Name: simplygopy
Version: 2021.5.1
Summary: Python 3 module to talk to SimplyGo from Transit Link in Singapore
Home-page: https://github.com/TheDJVG/SimplyGoPy
Author: D. van Gorkum
Author-email: djvg@djvg.net
License: UNKNOWN
Platform: UNKNOWN
Classifier: Programming Language :: Python :: 3
Classifier: Programming Language :: Python :: 3.6
Classifier: Programming Language :: Python :: 3.7
Classifier: Programming Language :: Python :: 3.8
Classifier: License :: OSI Approved :: MIT License
Classifier: Operating System :: OS Independent
Requires-Python: >=3.6
Requires-Dist: requests
